win32mica/__init__.py
win32mica-3.0.dist-info/LICENSE
win32mica-3.0.dist-info/METADATA
win32mica-3.0.dist-info/WHEEL
win32mica-3.0.dist-info/top_level.txt
win32mica-3.0.dist-info/RECORD
