Metadata-Version: 2.1
Name: win32mica
Version: 3.0
Summary: Apply mica background (if supported) and immersive dark mode to Windows 11 Win32 apps made with python, such as Tkinter or PyQt/PySide apps
Home-page: https://github.com/marticliment/win32mica
Author: Martí Climent
Author-email: marticlilop@gmail.com
Project-URL: Bug Tracker, https://github.com/marticliment/win32mica/issues
Classifier: Intended Audience :: Developers
Classifier: Programming Language :: Python :: 3
Classifier: License :: OSI Approved :: MIT License
Classifier: Operating System :: Microsoft :: Windows
Requires-Python: >=3.6
License-File: LICENSE
